{
    "pageNumber": 0,
    "data": [
        {
            "id": "120774127",
            "title": "Meet the new Roku Streaming Stick (Model 3800)",
            "date_created": "1506948387",
            "loginId": "1758854",
            "tags": "",
            "description": "Powerful. Portable. Enhanced Voice Remote.The Roku\u00ae Streaming Stick\u00ae gives you smooth streaming at home or on-the-go.* You can even hide it behind your TV. \n\nTired of juggling remotes? Our new voice remote lets you easily control your TV with buttons for TV power and volume.***\n\nWatch what you love. Enjoy 500,000+ movies & TV episodes across thousands of free or paid channels.**\n\n*For portability outside the house, bring your Roku remote, a wireless-connected phone\/computer & USB power cable.\n**Channels can change and vary by country.\n***TV power and volume buttons require a compatible TV. \n\nLearn more and purchase here: http:\/\/bit.ly\/2cVhlcN\n\nLike us on Facebook: https:\/\/www.facebook.com\/roku\nFollow us on Twitter: https:\/\/twitter.com\/RokuPlayer\nFollow us on Instagram: https:\/\/www.instagram.com\/rokuplayer\/\nSubscribe on YouTube: http:\/\/bit.ly\/SubRoku",
            "asset": {
                "type": "youtube",
                "thumbnailUrl": "https:\/\/i.ytimg.com\/vi\/NKr4DRpjg3M\/maxresdefault.jpg",
                "uploadDate": 1506948387,
                "videoId": "NKr4DRpjg3M",
                "title": "Meet the new Roku Streaming Stick (Model 3800)",
                "description": "Powerful. Portable. Enhanced Voice Remote.The Roku\u00ae Streaming Stick\u00ae gives you smooth streaming at home or on-the-go.* You can even hide it behind your TV. \n\nTired of juggling remotes? Our new voice remote lets you easily control your TV with buttons for TV power and volume.***\n\nWatch what you love. Enjoy 500,000+ movies & TV episodes across thousands of free or paid channels.**\n\n*For portability outside the house, bring your Roku remote, a wireless-connected phone\/computer & USB power cable.\n**Channels can change and vary by country.\n***TV power and volume buttons require a compatible TV. \n\nLearn more and purchase here: http:\/\/bit.ly\/2cVhlcN\n\nLike us on Facebook: https:\/\/www.facebook.com\/roku\nFollow us on Twitter: https:\/\/twitter.com\/RokuPlayer\nFollow us on Instagram: https:\/\/www.instagram.com\/rokuplayer\/\nSubscribe on YouTube: http:\/\/bit.ly\/SubRoku",
                "author": "Roku",
                "mediaDuration": 87,
                "prettyDuration": "00:01:27",
                "views": "473",
                "uploadAsset": false,
                "quality": ""
            },
            "parentId": "94403910",
            "url": "\/roku-channel\/meet-the-new-roku-streaming-stick-model-3800\/94403910-120774127"
        },
        {
            "id": "125345928",
            "title": "Canada: meet the new Roku Express (Model 3900)",
            "date_created": "1508958071",
            "loginId": "1758854",
            "tags": "",
            "description": "Want to start streaming? Roku Express is now 5X more powerful. Our best-priced player, delivers a smooth HD streaming experience on your big-screen TV. \n\nIt\u2019s easy to get started. Just plug it in, connect to the Internet, and start streaming. \n\nLearn more about the Roku Express in Canada: http:\/\/bit.ly\/2zeKCG8\n\nLike us on Facebook: https:\/\/www.facebook.com\/roku\nFollow us on Twitter: https:\/\/twitter.com\/RokuPlayer\nFollow us on Instagram: https:\/\/www.instagram.com\/rokuplayer\/\nSubscribe on YouTube: http:\/\/bit.ly\/SubRoku",
            "asset": {
                "type": "youtube",
                "thumbnailUrl": "https:\/\/i.ytimg.com\/vi\/21eDr646JKg\/maxresdefault.jpg",
                "uploadDate": 1508958071,
                "videoId": "21eDr646JKg",
                "title": "Canada: meet the new Roku Express (Model 3900)",
                "description": "Want to start streaming? Roku Express is now 5X more powerful. Our best-priced player, delivers a smooth HD streaming experience on your big-screen TV. \n\nIt\u2019s easy to get started. Just plug it in, connect to the Internet, and start streaming. \n\nLearn more about the Roku Express in Canada: http:\/\/bit.ly\/2zeKCG8\n\nLike us on Facebook: https:\/\/www.facebook.com\/roku\nFollow us on Twitter: https:\/\/twitter.com\/RokuPlayer\nFollow us on Instagram: https:\/\/www.instagram.com\/rokuplayer\/\nSubscribe on YouTube: http:\/\/bit.ly\/SubRoku",
                "author": "Roku",
                "mediaDuration": 61,
                "prettyDuration": "00:01:01",
                "views": "22",
                "uploadAsset": false,
                "quality": ""
            },
            "parentId": "94403910",
            "url": "\/roku-channel\/canada-meet-the-new-roku-express-model-3900\/94403910-125345928"
        },
        {
            "id": "125345929",
            "title": "Meet the new Roku Streaming Stick+ (Model 3810)",
            "date_created": "1508957181",
            "loginId": "1758854",
            "tags": "",
            "description": "Meet the Roku Streaming Stick+. Exceptional wireless. Stunning picture quality. Whether you\u2019re streaming in your home or in a hotel, the advanced wireless receiver gives you 4X the range.\n \nBrilliant 4K, HDR and HD. The Roku Streaming Stick+ optimizes what you\u2019re streaming for the best picture resolution possible, whether you\u2019re watching on an HD, 4K or HDR TV.\n\nTired of juggling remotes? Our new voice remote lets you easily control your TV with buttons for TV power and volume. \n\nLearn more here: http:\/\/bit.ly\/2xUXP9x  \n\nLike us on Facebook: https:\/\/www.facebook.com\/roku\nFollow us on Twitter: https:\/\/twitter.com\/RokuPlayer\nFollow us on Instagram: https:\/\/www.instagram.com\/rokuplayer\/\nSubscribe on YouTube: http:\/\/bit.ly\/SubRoku",
            "asset": {
                "type": "youtube",
                "thumbnailUrl": "https:\/\/i.ytimg.com\/vi\/CK7EwQEtEi4\/maxresdefault.jpg",
                "uploadDate": 1508957181,
                "videoId": "CK7EwQEtEi4",
                "title": "Meet the new Roku Streaming Stick+ (Model 3810)",
                "description": "Meet the Roku Streaming Stick+. Exceptional wireless. Stunning picture quality. Whether you\u2019re streaming in your home or in a hotel, the advanced wireless receiver gives you 4X the range.\n \nBrilliant 4K, HDR and HD. The Roku Streaming Stick+ optimizes what you\u2019re streaming for the best picture resolution possible, whether you\u2019re watching on an HD, 4K or HDR TV.\n\nTired of juggling remotes? Our new voice remote lets you easily control your TV with buttons for TV power and volume. \n\nLearn more here: http:\/\/bit.ly\/2xUXP9x  \n\nLike us on Facebook: https:\/\/www.facebook.com\/roku\nFollow us on Twitter: https:\/\/twitter.com\/RokuPlayer\nFollow us on Instagram: https:\/\/www.instagram.com\/rokuplayer\/\nSubscribe on YouTube: http:\/\/bit.ly\/SubRoku",
                "author": "Roku",
                "mediaDuration": 104,
                "prettyDuration": "00:01:44",
                "views": "72",
                "uploadAsset": false,
                "quality": ""
            },
            "parentId": "94403910",
            "url": "\/roku-channel\/meet-the-new-roku-streaming-stick-model-3810\/94403910-125345929"
        },
        {
            "id": "125345933",
            "title": "Meet the new Roku Ultra (Model 4660)",
            "date_created": "1508957192",
            "loginId": "1758854",
            "tags": "",
            "description": "Our ultimate streaming experience.The Roku Ultra is our most powerful player with our best wireless performance. \n\nBrilliant picture quality creates an immersive experience. Whether your TV is HD, 4K or HDR, Roku Ultra will optimize your content for the best picture resolution possible.\n\nIt\u2019s fully loaded. Includes a new voice remote with TV power and volume buttons, private listening, lost-remote finder, access to 500,000+ movies and TV episodes and more.",
            "asset": {
                "type": "youtube",
                "thumbnailUrl": "https:\/\/i.ytimg.com\/vi\/DmMwK_iSTvY\/maxresdefault.jpg",
                "uploadDate": 1508957192,
                "videoId": "DmMwK_iSTvY",
                "title": "Meet the new Roku Ultra (Model 4660)",
                "description": "Our ultimate streaming experience.The Roku Ultra is our most powerful player with our best wireless performance. \n\nBrilliant picture quality creates an immersive experience. Whether your TV is HD, 4K or HDR, Roku Ultra will optimize your content for the best picture resolution possible.\n\nIt\u2019s fully loaded. Includes a new voice remote with TV power and volume buttons, private listening, lost-remote finder, access to 500,000+ movies and TV episodes and more.\n\nLearn more here: http:\/\/bit.ly\/2e1AV55\n\nLike us on Facebook: https:\/\/www.facebook.com\/roku\nFollow us on Twitter: https:\/\/twitter.com\/RokuPlayer\nFollow us on Instagram: https:\/\/www.instagram.com\/rokuplayer\/\nSubscribe on YouTube: http:\/\/bit.ly\/SubRoku",
                "author": "Roku",
                "mediaDuration": 115,
                "prettyDuration": "00:01:55",
                "views": "106",
                "uploadAsset": false,
                "quality": ""
            },
            "parentId": "94403910",
            "url": "\/roku-channel\/meet-the-new-roku-ultra-model-4660\/94403910-125345933"
        },
        {
            "id": "130705880",
            "title": "How to set up the Roku Ultra (Model 4660)",
            "date_created": "1511383595",
            "loginId": "1758854",
            "tags": "",
            "description": "Roku Ultra (model: 4660) supports 720p HD, 1080p Full HD, 4K Ultra HD (UHD) and 4K Ultra HD HDR (High Dynamic Range) and ships with an Enhanced \u201cpoint-anywhere\u201d remote with TV power and volume buttons, voice search, remote finder, gaming buttons and private listening via a headphone jack on the remote.",
            "asset": {
                "type": "youtube",
                "thumbnailUrl": "https:\/\/i.ytimg.com\/vi\/psDNj3j50lg\/maxresdefault.jpg",
                "uploadDate": 1511383595,
                "videoId": "psDNj3j50lg",
                "title": "How to set up the Roku Ultra (Model 4660)",
                "description": "Roku Ultra (model: 4660) supports 720p HD, 1080p Full HD, 4K Ultra HD (UHD) and 4K Ultra HD HDR (High Dynamic Range) and ships with an Enhanced \u201cpoint-anywhere\u201d remote with TV power and volume buttons, voice search, remote finder, gaming buttons and private listening via a headphone jack on the remote. \n\nThis article describes the product in more detail and outlines the setup steps: http:\/\/bit.ly\/2A4fdI2",
                "author": "Roku",
                "mediaDuration": 432,
                "prettyDuration": "00:07:12",
                "views": "71",
                "uploadAsset": false,
                "quality": ""
            },
            "parentId": "94403910",
            "url": "\/roku-channel\/how-to-set-up-the-roku-ultra-model-4660\/94403910-130705880"
        },
        {
            "id": "94403820",
            "title": "New Roku Streaming Stick 3600R - Quick Overview",
            "date_created": "1459861376",
            "loginId": "1758854",
            "tags": "",
            "description": "Big streaming power in a pocket-sized stick. The new 2016 Roku\u00ae Streaming Stick\u00ae delivers powerful performance with a quad-core processor and dual-band wireless. Access Amazon Prime Video, VUDU, Google Play, Netflix, Hulu, and more for 300,000+ movies and TV episodes.* And easily stream to different HDTVs in your home, dorm, or hotel room.\n\n* Subscription or other payment may be required to access certain content. Channel availability subject to change and content may\nnot be available in all regions Roku players are sold.",
            "asset": {
                "type": "youtube",
                "thumbnailUrl": "https:\/\/i.ytimg.com\/vi\/9emKpHrbq6Y\/hqdefault.jpg",
                "uploadDate": 1459861376,
                "videoId": "9emKpHrbq6Y",
                "title": "New Roku Streaming Stick (3600R - 2016 Version) - Quick Overview",
                "description": "Big streaming power in a pocket-sized stick. The new 2016 Roku\u00ae Streaming Stick\u00ae delivers powerful performance with a quad-core processor and dual-band wireless. Access Amazon Prime Video, VUDU, Google Play, Netflix, Hulu, and more for 300,000+ movies and TV episodes.* And easily stream to different HDTVs in your home, dorm, or hotel room.\n\n* Subscription or other payment may be required to access certain content. Channel availability subject to change and content may\nnot be available in all regions Roku players are sold.\n\nGet your power-packed Roku Streaming Stick here: http:\/\/bit.ly\/239cs3m\n\nFollow us on social media!\n\nFacebook: https:\/\/www.facebook.com\/roku\/\nTwitter: https:\/\/twitter.com\/RokuPlayer \nInstagram: https:\/\/www.instagram.com\/rokuplayer\/",
                "author": "Roku",
                "mediaDuration": 27,
                "prettyDuration": "00:00:27",
                "views": "6427",
                "uploadAsset": false,
                "quality": ""
            },
            "parentId": "94403910",
            "url": "\/roku-channel\/new-roku-streaming-stick-3600r-2016-version-quick-overview\/94403910-94403820"
        }
    ]
}