{
    "title": "Sonance Channel",
    "description": null,
    "referenceId": null,
    "date_created": "1492799378",
    "date_modified": "1492799378",
    "tags": null,
    "sourceId": null,
    "duration": null,
    "status": "pending",
    "visibility": "1",
    "id": "87753750",
    "loginId": "1758854",
    "entityType": "3",
    "titleTextEncoded": "Sonance-Channel",
    "category": null,
    "settings": "{\"canvasImage\":\"default_canvas3.jpg\",\"colorClass\":\"light\",\"canvasType\":\"gallery\"}",
    "transcripts": null
}