{
    "title": "Jaybird RUN True Wireless Sport Headphones",
    "description": "Sport is finally wire-free! Jaybird RUN true wireless sport headphones deliver big custom sound in a super-small, sleek, light, sweat-proof design that comfortably fits all ears \u2013 just you, your music and your run, forget everything else.",
    "referenceId": "9-RdzF6YwzY",
    "date_created": "1505387619",
    "date_modified": "1505928076",
    "tags": "",
    "sourceId": "4",
    "VIDEO_LENGTH": "SHORT",
    "duration": "104",
    "status": "approved",
    "visibility": "1",
    "video_type": "first_look",
    "featured_category": null,
    "brand1": "jaybird",
    "main_category": "audio",
    "sub_category": "audio_headphones",
    "brand_filter": "i_j",
    "sort_order": null,
    "YETI": null,
    "Chantal": null,
    "Rode": null,
    "Rabbit": null,
    "Hunter": null,
    "Casablanca": null,
    "Marshall": null,
    "Thrustmaster": null,
    "First_Alert": null,
    "ANKR": null,
    "Maglite": null,
    "ClassicFlame": null,
    "Zera": null,
    "MantelMount": null,
    "Revolar": null,
    "JOBY": null,
    "Coyote": null,
    "Amplifi": null,
    "Solidsteel": null,
    "The_Galley": null,
    "Shavel": null,
    "Zeiss": null,
    "Chipolo": null,
    "mJoose": null,
    "B_W_International": null,
    "Luminox": null,
    "Lifesmart": null,
    "Muzik": null,
    "RadarMount": null,
    "VV_VI": "23",
    "CVV_VI": null,
    "engagement_score": null,
    "conversion_score": null,
    "user_id": "0",
    "id": "117683522",
    "loginId": "1758854",
    "entityType": "1",
    "titleTextEncoded": "Jaybird-RUN-True-Wireless-Sport-Headphones",
    "category": "",
    "settings": "",
    "asset": {
        "type": "youtube",
        "thumbnailUrl": "https:\/\/i.ytimg.com\/vi\/9-RdzF6YwzY\/hqdefault.jpg",
        "uploadDate": 1505387619,
        "videoId": "9-RdzF6YwzY",
        "title": "Jaybird RUN True Wireless Sport Headphones",
        "description": "Sport is finally wire-free! Jaybird RUN true wireless sport headphones deliver big custom sound in a super-small, sleek, light, sweat-proof design that comfortably fits all ears \u2013 just you, your music and your run, forget everything else.\n\nLearn more: https:\/\/www.jaybirdsport.com\/en-us\/run-true-wireless-sport-headphones.html",
        "author": "Jaybird",
        "mediaDuration": 104,
        "prettyDuration": "00:01:44",
        "views": "2658",
        "uploadAsset": false,
        "quality": ""
    },
    "transcripts": "",
    "metrics_statistics": {
        "VV_VI": {
            "lastUpdatedDate": "2018-04-01"
        }
    },
    "tvp_profiles": [
        "8",
        "11"
    ],
    "tvp_profiles_manual": "",
    "tvp_profiles_maxscore": 10957.27,
    "tvp_enhanced_search": null,
    "tvp_enhanced_anti": null,
    "tvp_enhanced_brand": null,
    "tvp_enhanced_video_images": null,
    "tvp_enhanced_transcript": null
}