{
    "title": "Frigidaire Side by Side Refrigerator FFSS2625T",
    "description": "Features:\n\nAdjustable Interior Storage \nOver 100 ways to organize and customize your refrigerator. Details vary by model\nMulti-Level LED Lighting \nCorner-to-corner LED lighting throughout the refrigerator for better visibility\nPureSource 3\u00ae \nPureSource 3\u00ae Water Filtration gives you cleaner, better tasting water at your fingertips\nDeli Drawer \nKeeps sandwich meats and cheeses organized in a convenient location\nStore-More\u2122 Humidity-Controlled Crisper Drawers \nKeep your fruits and vegetables fresh in our humidity-controlled crisper drawers\nStore-More\u2122 Capacity \nOur large capacity refrigerator gives you room to store more\nStore-More\u2122 Gallon Door Bins \nDoor storage gives you room for larger items \u2014 like a gallon of milk\nClear Dairy Door\nStore-More\u2122 Shelves \nMore space to store your food with edge-to-edge shelves\nFilter Change Alert\nControl Lock Option\nReady-Select\u00ae Controls\nEasily select options with the touch of a button\nEnergy Saver Plus Technology \nOur refrigerator will automatically go into an energy-saving mode if not opened for 24 hours\nSpecifications:\n\nCapacity\n\nTotal Capacity (Cu. Ft.): 25.5\nRefrigerator Capacity (Cu. Ft.): 16.5\nFreezer Capacity (Cu. Ft.): 9.0\nGeneral\n\nDoor Design: UltraSoft\nDoor Handle Design: Color-Coordinated\nCabinet Finish: Color-Coordinated\nDoor Stops \/ Door Closers: Yes \/ Yes\nDoor Hinge Covers: Hidden\nRollers \u2013 Front \/ Rear: Adjustable \/ Yes\nEnergy Saver Plus Technology: Yes\nWater Filter Location: Top Right Rear\nDispenser\n\nControls: Ready-Select\u00ae\nDispenser Design: Tall, 2-Paddle\nNumber of Dispenser Buttons: 5\nCrushed Ice \/ Cube Ice \/ Water: Yes \/ Yes \/ Yes\nControl Lock \/ Light: Yes \/ Yes\nWater Filter Change Indicator Light: Yes\nRefrigerator\n\nInterior Lighting: LED\nWater Filter Type: PureSource 3\u00ae\nFixed Shelves: 2 Flat Glass\nDeli Drawer: Yes\nUpper Crisper \/ Lower Crisper: 1 Clear \/ 1 Clear\nHumidity Controls: 1\nDairy Compartment: 1 Clear\nFixed Door Bins: 2 Two-Liter Clear\nAdjustable Door Bins: 2 One-Gallon Clear\nFreezer\n\nDoor Bins: 4 White\nFixed Shelves: 1 Flip-Out \/ 2 Wire\nFull Freezer Baskets: 1 Plastic\nLighting: LED\nElectrical\n\nPower Supply Connection Location: Right Bottom Rear\nWater Inlet Connection Location: Left Bottom Rear\nVoltage Rating: 120V \/ 60Hz\nConnected Load (kW Rating) @ 120 Volts: 1.02\nAmps @ 120 Volts: 8.5\nMinimum Circuit Required (Amps): 15",
    "referenceId": "tQIBW62wmrQ",
    "date_created": "1508351985",
    "date_modified": "1508352701",
    "tags": "",
    "sourceId": "4",
    "VIDEO_LENGTH": "SHORT",
    "duration": "54",
    "status": "approved",
    "visibility": "1",
    "video_type": "product_tour",
    "featured_category": "featured_yes",
    "brand1": "frigidaire",
    "main_category": "appliances",
    "sub_category": "appliances_refrigerators",
    "brand_filter": "e_f",
    "sort_order": null,
    "YETI": null,
    "Chantal": null,
    "Rode": null,
    "Rabbit": null,
    "Hunter": null,
    "Casablanca": null,
    "Marshall": null,
    "Thrustmaster": null,
    "First_Alert": null,
    "ANKR": null,
    "Maglite": null,
    "ClassicFlame": null,
    "Zera": null,
    "MantelMount": null,
    "Revolar": null,
    "JOBY": null,
    "Coyote": null,
    "Amplifi": null,
    "Solidsteel": null,
    "The_Galley": null,
    "Shavel": null,
    "Zeiss": null,
    "Chipolo": null,
    "mJoose": null,
    "B_W_International": null,
    "Luminox": null,
    "Lifesmart": null,
    "Muzik": null,
    "RadarMount": null,
    "VV_VI": "14",
    "CVV_VI": null,
    "engagement_score": null,
    "conversion_score": null,
    "user_id": "0",
    "id": "123578765",
    "loginId": "1758854",
    "entityType": "1",
    "titleTextEncoded": "Frigidaire-Side-by-Side-Refrigerator-FFSS2625SS",
    "category": null,
    "settings": null,
    "asset": {
        "type": "youtube",
        "author": "Abt Electronics",
        "hdvFlag": 1,
        "description": "",
        "tags": "",
        "thumbnailUrl": "https:\/\/i.ytimg.com\/vi\/tQIBW62wmrQ\/maxresdefault.jpg",
        "videoId": "tQIBW62wmrQ",
        "mediaDuration": 54,
        "prettyDuration": "00:00:54",
        "uploadAsset": false,
        "quality": ""
    },
    "transcripts": null,
    "metrics_statistics": {
        "VV_VI": {
            "lastUpdatedDate": "2018-06-07"
        }
    },
    "tvp_profiles": [
        "18"
    ],
    "tvp_profiles_manual": null,
    "tvp_profiles_maxscore": 4412.9,
    "tvp_enhanced_search": null,
    "tvp_enhanced_anti": null,
    "tvp_enhanced_brand": null,
    "tvp_enhanced_video_images": null,
    "tvp_enhanced_transcript": null
}