{
    "title": "Schlaum\u00e4use is an app that helps kids learn German",
    "description": ".",
    "referenceId": "FV-4YrIXcIg",
    "date_created": "1475736621",
    "date_modified": "1488319950",
    "tags": "",
    "sourceId": "4",
    "VIDEO_LENGTH": "SHORT",
    "duration": "133",
    "status": "approved",
    "visibility": "1",
    "video_type": null,
    "featured_category": null,
    "brand1": null,
    "main_category": null,
    "sub_category": null,
    "brand_filter": null,
    "sort_order": null,
    "YETI": null,
    "Chantal": null,
    "Rode": null,
    "Rabbit": null,
    "Hunter": null,
    "Casablanca": null,
    "Marshall": null,
    "Thrustmaster": null,
    "First_Alert": null,
    "ANKR": null,
    "Maglite": null,
    "ClassicFlame": null,
    "Zera": null,
    "MantelMount": null,
    "Revolar": null,
    "JOBY": null,
    "Coyote": null,
    "Amplifi": null,
    "Solidsteel": null,
    "The_Galley": null,
    "Shavel": null,
    "Zeiss": null,
    "Chipolo": null,
    "mJoose": null,
    "B_W_International": null,
    "Luminox": null,
    "Lifesmart": null,
    "Muzik": null,
    "RadarMount": null,
    "VV_VI": null,
    "CVV_VI": null,
    "engagement_score": null,
    "conversion_score": null,
    "user_id": "0",
    "id": "69549325",
    "loginId": "1758854",
    "entityType": "1",
    "titleTextEncoded": "Schlaum\u00e4use-is-an-app-that-helps-kids-learn-German",
    "category": "",
    "settings": "",
    "asset": {
        "type": "youtube",
        "thumbnailUrl": "https:\/\/i.ytimg.com\/vi\/FV-4YrIXcIg\/hqdefault.jpg",
        "uploadDate": 1475736621,
        "videoId": "FV-4YrIXcIg",
        "title": "Schlaum\u00e4use is an app that helps kids learn German",
        "description": "",
        "author": "Microsoft",
        "mediaDuration": 133,
        "prettyDuration": "00:02:13",
        "views": "1000",
        "uploadAsset": false,
        "quality": ""
    },
    "transcripts": "",
    "metrics_statistics": null,
    "tvp_profiles": [
        "12",
        "16",
        "25"
    ],
    "tvp_profiles_manual": null,
    "tvp_profiles_maxscore": 277.90836,
    "tvp_enhanced_search": null,
    "tvp_enhanced_anti": null,
    "tvp_enhanced_brand": null,
    "tvp_enhanced_video_images": null,
    "tvp_enhanced_transcript": null
}