{
    "title": "Lose the noise & wires. Lose yourself in the music.",
    "description": "Bose\u00ae QuietComfort\u00ae 35 wireless headphones are engineered with world-class noise cancellation that makes quiet sound quieter and music sound better. Connect easily to your devices with Bluetooth\u00ae and NFC pairing and get up to 20 hours of wireless listening per battery charge.",
    "referenceId": "ul2oWjrvGUc",
    "date_created": "1466457749",
    "date_modified": "1499877988",
    "tags": "",
    "sourceId": "4",
    "VIDEO_LENGTH": "SHORT",
    "duration": "52",
    "status": "approved",
    "visibility": "1",
    "video_type": "product_tour",
    "featured_category": null,
    "brand1": "bose",
    "main_category": "audio",
    "sub_category": "audio_headphones",
    "brand_filter": "__b",
    "sort_order": null,
    "YETI": null,
    "Chantal": null,
    "Rode": null,
    "Rabbit": null,
    "Hunter": null,
    "Casablanca": null,
    "Marshall": null,
    "Thrustmaster": null,
    "First_Alert": null,
    "ANKR": null,
    "Maglite": null,
    "ClassicFlame": null,
    "Zera": null,
    "MantelMount": null,
    "Revolar": null,
    "JOBY": null,
    "Coyote": null,
    "Amplifi": null,
    "Solidsteel": null,
    "The_Galley": null,
    "Shavel": null,
    "Zeiss": null,
    "Chipolo": null,
    "mJoose": null,
    "B_W_International": null,
    "Luminox": null,
    "Lifesmart": null,
    "Muzik": null,
    "RadarMount": null,
    "VV_VI": "9",
    "CVV_VI": null,
    "engagement_score": null,
    "conversion_score": null,
    "user_id": "0",
    "id": "69622724",
    "loginId": "1758854",
    "entityType": "1",
    "titleTextEncoded": "Lose-the-noise-wires-Lose-yourself-in-the-music",
    "category": "",
    "settings": "",
    "asset": {
        "type": "youtube",
        "thumbnailUrl": "https:\/\/i.ytimg.com\/vi\/ul2oWjrvGUc\/hqdefault.jpg",
        "uploadDate": 1466457749,
        "videoId": "ul2oWjrvGUc",
        "title": "Lose the noise & wires. Lose yourself in the music.",
        "description": "Bose\u00ae QuietComfort\u00ae 35 wireless headphones are engineered with world-class noise cancellation that makes quiet sound quieter and music sound better. Connect easily to your devices with Bluetooth\u00ae and NFC pairing and get up to 20 hours of wireless listening per battery charge.",
        "author": "Bose",
        "mediaDuration": 52,
        "prettyDuration": "00:00:52",
        "views": "613114",
        "uploadAsset": false,
        "quality": ""
    },
    "transcripts": "",
    "metrics_statistics": {
        "VV_VI": {
            "lastUpdatedDate": "2018-06-07"
        }
    },
    "tvp_profiles": [
        "11",
        "22"
    ],
    "tvp_profiles_manual": null,
    "tvp_profiles_maxscore": 1453.6476,
    "tvp_enhanced_search": null,
    "tvp_enhanced_anti": null,
    "tvp_enhanced_brand": null,
    "tvp_enhanced_video_images": null,
    "tvp_enhanced_transcript": null
}