{
    "title": "ProMaster Bluetooth Selfie Trigger Camera Remote PRO3372 - Overview",
    "description": "ProMaster Bluetooth Selfie Trigger Camera Remote - PRO3372 http:\/\/www.abt.com\/product\/94051\/ProMaster-PRO3372.html\n\nThe ProMaster Bluetooth Selfie Trigger Camera Remote is pocket-size easy to carry easy to set up easy to use. Now everyone can be in the pictures with this bluetooth remote shutter. Compatible with iPhone and Android\u2122 smartphones using Bluetooth 3.0.\nCompatibility:\n\u2022 Android 4.2.2 OS or greater and iOS 6.0 or greater devices",
    "referenceId": "eqoWJxIDBSU",
    "date_created": "1441222877",
    "date_modified": "1476910821",
    "tags": "",
    "sourceId": "4",
    "VIDEO_LENGTH": "SHORT",
    "duration": "79",
    "status": "approved",
    "visibility": "1",
    "video_type": null,
    "featured_category": null,
    "brand1": null,
    "main_category": null,
    "sub_category": null,
    "brand_filter": null,
    "sort_order": null,
    "YETI": null,
    "Chantal": null,
    "Rode": null,
    "Rabbit": null,
    "Hunter": null,
    "Casablanca": null,
    "Marshall": null,
    "Thrustmaster": null,
    "First_Alert": null,
    "ANKR": null,
    "Maglite": null,
    "ClassicFlame": null,
    "Zera": null,
    "MantelMount": null,
    "Revolar": null,
    "JOBY": null,
    "Coyote": null,
    "Amplifi": null,
    "Solidsteel": null,
    "The_Galley": null,
    "Shavel": null,
    "Zeiss": null,
    "Chipolo": null,
    "mJoose": null,
    "B_W_International": null,
    "Luminox": null,
    "Lifesmart": null,
    "Muzik": null,
    "RadarMount": null,
    "VV_VI": "5",
    "CVV_VI": null,
    "engagement_score": null,
    "conversion_score": null,
    "user_id": "0",
    "id": "69863689",
    "loginId": "1758854",
    "entityType": "1",
    "titleTextEncoded": "ProMaster-Bluetooth-Selfie-Trigger-Camera-Remote-PRO3372-Overview",
    "category": "",
    "settings": "",
    "asset": {
        "type": "youtube",
        "thumbnailUrl": "https:\/\/i.ytimg.com\/vi\/eqoWJxIDBSU\/hqdefault.jpg",
        "uploadDate": 1441222877,
        "videoId": "eqoWJxIDBSU",
        "title": "ProMaster Bluetooth Selfie Trigger Camera Remote PRO3372 - Overview",
        "description": "ProMaster Bluetooth Selfie Trigger Camera Remote - PRO3372 http:\/\/www.abt.com\/product\/94051\/ProMaster-PRO3372.html\n\nThe ProMaster Bluetooth Selfie Trigger Camera Remote is pocket-size easy to carry easy to set up easy to use. Now everyone can be in the pictures with this bluetooth remote shutter. Compatible with iPhone and Android\u2122 smartphones using Bluetooth 3.0.\nCompatibility:\n\u2022 Android 4.2.2 OS or greater and iOS 6.0 or greater devices",
        "author": "Abt",
        "mediaDuration": 79,
        "prettyDuration": "00:01:19",
        "views": "212",
        "uploadAsset": false,
        "quality": ""
    },
    "transcripts": "",
    "metrics_statistics": {
        "VV_VI": {
            "lastUpdatedDate": "2017-11-14"
        }
    },
    "tvp_profiles": [
        "11"
    ],
    "tvp_profiles_manual": null,
    "tvp_profiles_maxscore": 0,
    "tvp_enhanced_search": null,
    "tvp_enhanced_anti": null,
    "tvp_enhanced_brand": null,
    "tvp_enhanced_video_images": null,
    "tvp_enhanced_transcript": null
}