{
    "title": "Tumi Alpha Bravo Luke Roll-Top Leather Backpack 92388 - Overview",
    "description": "Tumi Alpha Bravo Luke Roll-Top Leather Backpack - 92388 - DARK BROWN\nhttp:\/\/www.abt.com\/product\/92806\/Tumi-92388DARKBROWN.html?utm_source=youtube&utm_medium=video&utm_campaign=092388DB2_20160302\n\nHandsomely reimagined in rich leather this generously-sized roll top backpack tote was designed to be stuffed. Secure your phone tablet and laptop plus papers or files and enough clothes to get you through the weekend. Comfortable padded backpack straps. Top zip closure\nFeatures:\n\u2022 Primary Material:\no Leather \n\u2022 Laptop Dimensions:\no Fits: up to 15\no H: 15.75\no W: 12.25\no D: 1.5\n\u2022 Exterior Features:\no Leather top carry handle\no Adjustable shoulder strap\no Roll-top fold over main compartment\no Zip entry to main compartment\no Multiple front zip pockets\no 1 side zip pocket\no Main and back compartment separated by zipper\n\u2022 Interior Features:\no iPad pocket\no 15 laptop compartment\no 2 open pockets\no 1 media pocket\no 1 zipped pocket\no 2 business card pockets\no 1 pen loop\no Key leash",
    "referenceId": "27P3A46dcz8",
    "date_created": "1456950533",
    "date_modified": "1476296265",
    "tags": "",
    "sourceId": "4",
    "VIDEO_LENGTH": "SHORT",
    "duration": "49",
    "status": "approved",
    "visibility": "1",
    "video_type": null,
    "featured_category": null,
    "brand1": null,
    "main_category": null,
    "sub_category": null,
    "brand_filter": null,
    "sort_order": null,
    "YETI": null,
    "Chantal": null,
    "Rode": null,
    "Rabbit": null,
    "Hunter": null,
    "Casablanca": null,
    "Marshall": null,
    "Thrustmaster": null,
    "First_Alert": null,
    "ANKR": null,
    "Maglite": null,
    "ClassicFlame": null,
    "Zera": null,
    "MantelMount": null,
    "Revolar": null,
    "JOBY": null,
    "Coyote": null,
    "Amplifi": null,
    "Solidsteel": null,
    "The_Galley": null,
    "Shavel": null,
    "Zeiss": null,
    "Chipolo": null,
    "mJoose": null,
    "B_W_International": null,
    "Luminox": null,
    "Lifesmart": null,
    "Muzik": null,
    "RadarMount": null,
    "VV_VI": "37",
    "CVV_VI": null,
    "engagement_score": null,
    "conversion_score": null,
    "user_id": "0",
    "id": "69863291",
    "loginId": "1758854",
    "entityType": "1",
    "titleTextEncoded": "Tumi-Alpha-Bravo-Luke-Roll-Top-Leather-Backpack-92388-Overview",
    "category": "",
    "settings": "",
    "asset": {
        "type": "youtube",
        "thumbnailUrl": "https:\/\/i.ytimg.com\/vi\/27P3A46dcz8\/hqdefault.jpg",
        "uploadDate": 1456950533,
        "videoId": "27P3A46dcz8",
        "title": "Tumi Alpha Bravo Luke Roll-Top Leather Backpack 92388 - Overview",
        "description": "Tumi Alpha Bravo Luke Roll-Top Leather Backpack - 92388 - DARK BROWN\nhttp:\/\/www.abt.com\/product\/92806\/Tumi-92388DARKBROWN.html?utm_source=youtube&utm_medium=video&utm_campaign=092388DB2_20160302\n\nHandsomely reimagined in rich leather this generously-sized roll top backpack tote was designed to be stuffed. Secure your phone tablet and laptop plus papers or files and enough clothes to get you through the weekend. Comfortable padded backpack straps. Top zip closure\nFeatures:\n\u2022 Primary Material:\no Leather \n\u2022 Laptop Dimensions:\no Fits: up to 15\no H: 15.75\no W: 12.25\no D: 1.5\n\u2022 Exterior Features:\no Leather top carry handle\no Adjustable shoulder strap\no Roll-top fold over main compartment\no Zip entry to main compartment\no Multiple front zip pockets\no 1 side zip pocket\no Main and back compartment separated by zipper\n\u2022 Interior Features:\no iPad pocket\no 15 laptop compartment\no 2 open pockets\no 1 media pocket\no 1 zipped pocket\no 2 business card pockets\no 1 pen loop\no Key leash",
        "author": "Abt",
        "mediaDuration": 49,
        "prettyDuration": "00:00:49",
        "views": "3748",
        "uploadAsset": false,
        "quality": ""
    },
    "transcripts": "",
    "metrics_statistics": "{\"VV_VI\":{\"lastUpdatedDate\":\"2017-05-22\",\"engagement_score\":{\"lastUpdatedDate\":\"2017-05-26\"}}}",
    "tvp_profiles": [
        "21"
    ],
    "tvp_profiles_manual": null,
    "tvp_profiles_maxscore": 0,
    "tvp_enhanced_search": null,
    "tvp_enhanced_anti": null,
    "tvp_enhanced_brand": null,
    "tvp_enhanced_video_images": null,
    "tvp_enhanced_transcript": null
}