{
    "title": "Canon PowerShot SX710 HS 20.3 Megapixel Digital Camera 0109C001 - Overview",
    "description": "Canon PowerShot SX710 HS Black 20.3 Megapixel Digital Camera - SX710HSBK - 0109C001 http:\/\/www.abt.com\/product\/89192\/Canon-0109C001.html\n\nFor capturing everything from vacation videos to everyday snaps youll want the high-zoom compact-body PowerShot SX710 HS camera by your side. Powerfully advanced yet easy to use this camera is prepared to handle a variety of situations. The amazing 30x Optical Zoom gives you the versatility you need to take your still images and breathtaking 1080p Full HD video to the next level with Intelligent IS and Zoom Framing Assist to keep even your highest zoom shots clear and steady. Experience sophisticated video capabilities including 60p\/30p\/24p and MP4 options the ability to add background music to your clips in Story Highlights and advanced Dynamic IS that keeps video steady even when you shoot while running or walking backwards. Built-in Wi-Fi and NFC make sharing what youve captured simple. With a 20.3 Megapixel High-Sensitivity CMOS sensor and DIGIC 6 Image Processor that create the Canon HS SYSTEM for excellent low-light performance all packed into a slim design this camera is perfect for travelers families and anyone who appreciates superb quality and performance.\nFeatures:\n\u2022 30x Optical Zoom (25\u2013750mm) \nWith the PowerShot SX710 HS camera in hand youll be impressed at the zooming capabilities of this slim compact digital camera. The amazing 30x Optical Zoom gets you just where you want to be: down on the field high atop a skyscraper deep into a landscape and much more. The cameras advanced technology helps ensure that images and videos are captured in outstanding quality with Intelligent IS that chooses the stabilization method thats best for the shooting conditions so images are virtually shake-free in a wide variety of situations.\n\u2022 Intelligent IS \nIts easy to capture clear steady images even in low light without using a tripod. Thats because the camera is equipped with Canons innovative Intelligent IS. The system automatically analyzes camera movement and applies the best shake correction method for the shooting situation \u2013 allowing you to focus on framing and capturing your shot. For stills the system selects from Normal IS Panning IS Macro (Hybrid) IS and Tripod modes. When shooting video the system selects from Dynamic IS Powered IS Macro (Hybrid) IS and active Tripod IS modes. Icons clearly mark the image stabilization mode whether youre shooting still images or video\n\u2022 Still Image Shooting\no Normal IS\nCorrects for a wide range of camera movement when shooting stills\no Panning IS \nPanning motion is detected so that IS does not interfere with desired camera movement\no Macro (Hybrid) IS \nCorrects for shift-type camera shake which typically occurs in macro (close-up) shooting\no Tripod \nWhen tripod use is detected the Image Stabilizer is stopped because it is not needed\n\u2022 Video Recording\no Dynamic IS\nEffective for video shooting at wide-angle focal lengths helping to eliminate the unwanted shaking that typically occurs while walking\no Powered IS \nCompensates for hand movement when shooting video at the telephoto end of the zoom range where camera shake is magnified\no Macro (Hybrid) IS\nCorrects for motion blur that is likely to occur when shooting video while walking. Also compensates for the shift-type camera shake common in macro shooting\no Active Tripod IS \nWhen shooting video while using a tripod the image stabilization is active to compensate for slight camera shake\n\u2022 Built-in NFC (Near Field Communication) \nPowerShot digital cameras with built-in NFC (Near Field Communication) technology eliminates the need to manually find and open the new Canon Camera Connect app on your mobile device. Simply touch the NFC icon on your camera to your compatible Android\u2122 device and the Camera Connect app will launch automatically for quick easy sharing of your images. Built-in NFC technology also makes it simpler to install the app. If the app hasnt been installed yet once you touch the devices together for the first time the download screen will display automatically. Now NFC helps ensure making a connection to a compatible Android\u2122 device truly seamless. Simply touch the camera against an NFC-equipped device with the Canon Camera Connect app installed and the Wi-Fi connection is established no camera operations required. Even if your camera is off NFC turns the camera on and establishes the connection (confirming the cameras nickname and privacy settings before the first connection is required)\n\u2022 Built-in Wi-Fi makes sharing quick and easy\nBuilt-in Wi-Fi technology for on-the-go convenience when you want to share your photos and videos with friends family and the whole world. Easily post your images to social networking and media sites \u2013 Facebook Twitter YouTube\u2122 Flickr and Google Drive\u2122 \u2013 through CANON iMAGE GATEWAY directly from your PowerShot camera or save them to the online photo album to share anytime anywhere. The camera can also connect dir",
    "referenceId": "_rqaUF6Cekk",
    "date_created": "1432750865",
    "date_modified": "1476982470",
    "tags": "",
    "sourceId": "4",
    "VIDEO_LENGTH": "SHORT",
    "duration": "131",
    "status": "approved",
    "visibility": "1",
    "video_type": null,
    "featured_category": null,
    "brand1": null,
    "main_category": null,
    "sub_category": null,
    "brand_filter": null,
    "sort_order": null,
    "YETI": null,
    "Chantal": null,
    "Rode": null,
    "Rabbit": null,
    "Hunter": null,
    "Casablanca": null,
    "Marshall": null,
    "Thrustmaster": null,
    "First_Alert": null,
    "ANKR": null,
    "Maglite": null,
    "ClassicFlame": null,
    "Zera": null,
    "MantelMount": null,
    "Revolar": null,
    "JOBY": null,
    "Coyote": null,
    "Amplifi": null,
    "Solidsteel": null,
    "The_Galley": null,
    "Shavel": null,
    "Zeiss": null,
    "Chipolo": null,
    "mJoose": null,
    "B_W_International": null,
    "Luminox": null,
    "Lifesmart": null,
    "Muzik": null,
    "RadarMount": null,
    "VV_VI": "11",
    "CVV_VI": null,
    "engagement_score": null,
    "conversion_score": null,
    "user_id": "0",
    "id": "69863819",
    "loginId": "1758854",
    "entityType": "1",
    "titleTextEncoded": "Canon-PowerShot-SX710-HS-20-3-Megapixel-Digital-Camera-0109C001-Overview",
    "category": "",
    "settings": "",
    "asset": {
        "type": "youtube",
        "thumbnailUrl": "https:\/\/i.ytimg.com\/vi\/_rqaUF6Cekk\/hqdefault.jpg",
        "uploadDate": 1432750865,
        "videoId": "_rqaUF6Cekk",
        "title": "Canon PowerShot SX710 HS 20.3 Megapixel Digital Camera 0109C001 - Overview",
        "description": "Canon PowerShot SX710 HS Black 20.3 Megapixel Digital Camera - SX710HSBK - 0109C001 http:\/\/www.abt.com\/product\/89192\/Canon-0109C001.html\n\nFor capturing everything from vacation videos to everyday snaps youll want the high-zoom compact-body PowerShot SX710 HS camera by your side. Powerfully advanced yet easy to use this camera is prepared to handle a variety of situations. The amazing 30x Optical Zoom gives you the versatility you need to take your still images and breathtaking 1080p Full HD video to the next level with Intelligent IS and Zoom Framing Assist to keep even your highest zoom shots clear and steady. Experience sophisticated video capabilities including 60p\/30p\/24p and MP4 options the ability to add background music to your clips in Story Highlights and advanced Dynamic IS that keeps video steady even when you shoot while running or walking backwards. Built-in Wi-Fi and NFC make sharing what youve captured simple. With a 20.3 Megapixel High-Sensitivity CMOS sensor and DIGIC 6 Image Processor that create the Canon HS SYSTEM for excellent low-light performance all packed into a slim design this camera is perfect for travelers families and anyone who appreciates superb quality and performance.\nFeatures:\n\u2022 30x Optical Zoom (25\u2013750mm) \nWith the PowerShot SX710 HS camera in hand youll be impressed at the zooming capabilities of this slim compact digital camera. The amazing 30x Optical Zoom gets you just where you want to be: down on the field high atop a skyscraper deep into a landscape and much more. The cameras advanced technology helps ensure that images and videos are captured in outstanding quality with Intelligent IS that chooses the stabilization method thats best for the shooting conditions so images are virtually shake-free in a wide variety of situations.\n\u2022 Intelligent IS \nIts easy to capture clear steady images even in low light without using a tripod. Thats because the camera is equipped with Canons innovative Intelligent IS. The system automatically analyzes camera movement and applies the best shake correction method for the shooting situation \u2013 allowing you to focus on framing and capturing your shot. For stills the system selects from Normal IS Panning IS Macro (Hybrid) IS and Tripod modes. When shooting video the system selects from Dynamic IS Powered IS Macro (Hybrid) IS and active Tripod IS modes. Icons clearly mark the image stabilization mode whether youre shooting still images or video\n\u2022 Still Image Shooting\no Normal IS\nCorrects for a wide range of camera movement when shooting stills\no Panning IS \nPanning motion is detected so that IS does not interfere with desired camera movement\no Macro (Hybrid) IS \nCorrects for shift-type camera shake which typically occurs in macro (close-up) shooting\no Tripod \nWhen tripod use is detected the Image Stabilizer is stopped because it is not needed\n\u2022 Video Recording\no Dynamic IS\nEffective for video shooting at wide-angle focal lengths helping to eliminate the unwanted shaking that typically occurs while walking\no Powered IS \nCompensates for hand movement when shooting video at the telephoto end of the zoom range where camera shake is magnified\no Macro (Hybrid) IS\nCorrects for motion blur that is likely to occur when shooting video while walking. Also compensates for the shift-type camera shake common in macro shooting\no Active Tripod IS \nWhen shooting video while using a tripod the image stabilization is active to compensate for slight camera shake\n\u2022 Built-in NFC (Near Field Communication) \nPowerShot digital cameras with built-in NFC (Near Field Communication) technology eliminates the need to manually find and open the new Canon Camera Connect app on your mobile device. Simply touch the NFC icon on your camera to your compatible Android\u2122 device and the Camera Connect app will launch automatically for quick easy sharing of your images. Built-in NFC technology also makes it simpler to install the app. If the app hasnt been installed yet once you touch the devices together for the first time the download screen will display automatically. Now NFC helps ensure making a connection to a compatible Android\u2122 device truly seamless. Simply touch the camera against an NFC-equipped device with the Canon Camera Connect app installed and the Wi-Fi connection is established no camera operations required. Even if your camera is off NFC turns the camera on and establishes the connection (confirming the cameras nickname and privacy settings before the first connection is required)\n\u2022 Built-in Wi-Fi makes sharing quick and easy\nBuilt-in Wi-Fi technology for on-the-go convenience when you want to share your photos and videos with friends family and the whole world. Easily post your images to social networking and media sites \u2013 Facebook Twitter YouTube\u2122 Flickr and Google Drive\u2122 \u2013 through CANON iMAGE GATEWAY directly from your PowerShot camera or save them to the online photo album to share anytime anywhere. The camera can also connect dir",
        "author": "Abt",
        "mediaDuration": 131,
        "prettyDuration": "00:02:11",
        "views": "24450",
        "uploadAsset": false,
        "quality": ""
    },
    "transcripts": "",
    "metrics_statistics": "{\"VV_VI\":{\"lastUpdatedDate\":\"2017-05-22\",\"engagement_score\":{\"lastUpdatedDate\":\"2017-05-26\"}}}",
    "tvp_profiles": [
        "7"
    ],
    "tvp_profiles_manual": null,
    "tvp_profiles_maxscore": 0,
    "tvp_enhanced_search": null,
    "tvp_enhanced_anti": null,
    "tvp_enhanced_brand": null,
    "tvp_enhanced_video_images": null,
    "tvp_enhanced_transcript": null
}