{
    "title": "Urban Armor Gear Scout iPad Mini 4 Folio Case IPDM4BLK - Overview",
    "description": "Urban Armor Gear Scout iPad Mini 4 Folio Case - IPDM4BLK http:\/\/www.abt.com\/product\/96366\/Urban-Armor-Gear-IPDM4BLK.html\n\nFeatures:\n\u2022 Feather-light composite construction\n\u2022 Impact resistant soft core\n\u2022 Water resistant grip material\n\u2022 Easy access to touch screen and ports\n\u2022 Smart cover and Frogskin Technology grip\n\u2022 Meets military drop-test standards (MIL STD 810G 516.6)",
    "referenceId": "Ojz613hFr4E",
    "date_created": "1450821087",
    "date_modified": "1476895504",
    "tags": "",
    "sourceId": "4",
    "VIDEO_LENGTH": "SHORT",
    "duration": "82",
    "status": "approved",
    "visibility": "1",
    "video_type": null,
    "featured_category": null,
    "brand1": null,
    "main_category": null,
    "sub_category": null,
    "brand_filter": null,
    "sort_order": null,
    "YETI": null,
    "Chantal": null,
    "Rode": null,
    "Rabbit": null,
    "Hunter": null,
    "Casablanca": null,
    "Marshall": null,
    "Thrustmaster": null,
    "First_Alert": null,
    "ANKR": null,
    "Maglite": null,
    "ClassicFlame": null,
    "Zera": null,
    "MantelMount": null,
    "Revolar": null,
    "JOBY": null,
    "Coyote": null,
    "Amplifi": null,
    "Solidsteel": null,
    "The_Galley": null,
    "Shavel": null,
    "Zeiss": null,
    "Chipolo": null,
    "mJoose": null,
    "B_W_International": null,
    "Luminox": null,
    "Lifesmart": null,
    "Muzik": null,
    "RadarMount": null,
    "VV_VI": "10",
    "CVV_VI": null,
    "engagement_score": null,
    "conversion_score": null,
    "user_id": "0",
    "id": "69863540",
    "loginId": "1758854",
    "entityType": "1",
    "titleTextEncoded": "Urban-Armor-Gear-Scout-iPad-Mini-4-Folio-Case-IPDM4BLK-Overview",
    "category": "",
    "settings": "",
    "asset": {
        "type": "youtube",
        "thumbnailUrl": "https:\/\/i.ytimg.com\/vi\/Ojz613hFr4E\/hqdefault.jpg",
        "uploadDate": 1450821087,
        "videoId": "Ojz613hFr4E",
        "title": "Urban Armor Gear Scout iPad Mini 4 Folio Case IPDM4BLK - Overview",
        "description": "Urban Armor Gear Scout iPad Mini 4 Folio Case - IPDM4BLK http:\/\/www.abt.com\/product\/96366\/Urban-Armor-Gear-IPDM4BLK.html\n\nFeatures:\n\u2022 Feather-light composite construction\n\u2022 Impact resistant soft core\n\u2022 Water resistant grip material\n\u2022 Easy access to touch screen and ports\n\u2022 Smart cover and Frogskin Technology grip\n\u2022 Meets military drop-test standards (MIL STD 810G 516.6)",
        "author": "Abt",
        "mediaDuration": 82,
        "prettyDuration": "00:01:22",
        "views": "5854",
        "uploadAsset": false,
        "quality": ""
    },
    "transcripts": "",
    "metrics_statistics": {
        "VV_VI": {
            "lastUpdatedDate": "2017-06-20"
        }
    },
    "tvp_profiles": [
        "11"
    ],
    "tvp_profiles_manual": null,
    "tvp_profiles_maxscore": 0,
    "tvp_enhanced_search": null,
    "tvp_enhanced_anti": null,
    "tvp_enhanced_brand": null,
    "tvp_enhanced_video_images": null,
    "tvp_enhanced_transcript": null
}